klap/__init__.py
klap/datasets/__init__.py
klap/datasets/helper.py
klap/datasets/synthetic.py
klap/kernels/__init__.py
klap/kernels/distance_kernel.py
klap/kernels/dot_product_kernel.py
klap/kernels/exponential.py
klap/kernels/gaussian.py
klap/kernels/gaussian_fast.py
klap/kernels/helper.py
klap/kernels/kernel_laplacian.py
klap/kernels/polynomial.py
klap-0.0.2.dist-info/LICENSE.txt
klap-0.0.2.dist-info/METADATA
klap-0.0.2.dist-info/WHEEL
klap-0.0.2.dist-info/top_level.txt
klap-0.0.2.dist-info/RECORD
